<annotation><folder>test_xmls</folder><filename>225.jpg</filename><path>./images225.jpg</path><source><database>Unknown</database></source><size><width>1200</width><height>648</height><depth>3</depth></size><segmented>0</segmented><object><name>coconut</name><pose>Unspecified</pose><truncated>0</truncated><difficult>0</difficult><bndbox><xmin>903.1579</xmin><ymin>193.55844</ymin><xmax>1006.31573</xmax><ymax>311.37662</ymax></bndbox></object><object><name>coconut</name><pose>Unspecified</pose><truncated>0</truncated><difficult>0</difficult><bndbox><xmin>972.6316</xmin><ymin>330.31168</ymin><xmax>1044.2104</xmax><ymax>406.05197</ymax></bndbox></object><object><name>coconut</name><pose>Unspecified</pose><truncated>0</truncated><difficult>0</difficult><bndbox><xmin>955.7894</xmin><ymin>418.67535</ymin><xmax>1052.6316</xmax><ymax>509.14285</ymax></bndbox></object><object><name>coconut</name><pose>Unspecified</pose><truncated>0</truncated><difficult>0</difficult><bndbox><xmin>810.5263</xmin><ymin>338.72726</ymin><xmax>901.0526</xmax><ymax>433.4026</ymax></bndbox></object><object><name>coconut</name><pose>Unspecified</pose><truncated>0</truncated><difficult>0</difficult><bndbox><xmin>896.8421</xmin><ymin>509.14285</ymin><xmax>983.1579</xmax><ymax>597.5065</ymax></bndbox></object><object><name>coconut</name><pose>Unspecified</pose><truncated>0</truncated><difficult>0</difficult><bndbox><xmin>795.7894</xmin><ymin>538.5974</ymin><xmax>892.6316</xmax><ymax>635.37665</ymax></bndbox></object><object><name>coconut</name><pose>Unspecified</pose><truncated>0</truncated><difficult>0</difficult><bndbox><xmin>690.52637</xmin><ymin>517.5584</ymin><xmax>791.579</xmax><ymax>626.96106</ymax></bndbox></object><object><name>coconut</name><pose>Unspecified</pose><truncated>0</truncated><difficult>0</difficult><bndbox><xmin>570.5263</xmin><ymin>513.35065</ymin><xmax>673.6842</xmax><ymax>614.33765</ymax></bndbox></object><object><name>coconut</name><pose>Unspecified</pose><truncated>0</truncated><difficult>0</difficult><bndbox><xmin>471.57895</xmin><ymin>511.24677</ymin><xmax>566.3158</xmax><ymax>616.4416</ymax></bndbox></object><object><name>coconut</name><pose>Unspecified</pose><truncated>0</truncated><difficult>0</difficult><bndbox><xmin>364.2105</xmin><ymin>519.66235</ymin><xmax>461.05264</xmax><ymax>610.1299</ymax></bndbox></object><object><name>coconut</name><pose>Unspecified</pose><truncated>0</truncated><difficult>0</difficult><bndbox><xmin>675.7895</xmin><ymin>244.05194</ymin><xmax>747.3684</xmax><ymax>330.31168</ymax></bndbox></object><object><name>coconut</name><pose>Unspecified</pose><truncated>0</truncated><difficult>0</difficult><bndbox><xmin>265.26315</xmin><ymin>355.55844</ymin><xmax>374.73685</xmax><ymax>456.54544</ymax></bndbox></object><object><name>coconut</name><pose>Unspecified</pose><truncated>0</truncated><difficult>0</difficult><bndbox><xmin>387.3684</xmin><ymin>366.07794</ymin><xmax>484.21054</xmax><ymax>456.54544</ymax></bndbox></object><object><name>coconut</name><pose>Unspecified</pose><truncated>0</truncated><difficult>0</difficult><bndbox><xmin>366.3158</xmin><ymin>452.33765</ymin><xmax>450.5263</xmax><ymax>551.22076</ymax></bndbox></object><object><name>coconut</name><pose>Unspecified</pose><truncated>0</truncated><difficult>0</difficult><bndbox><xmin>254.73685</xmin><ymin>460.75323</ymin><xmax>360.0</xmax><ymax>553.32465</ymax></bndbox></object><object><name>coconut</name><pose>Unspecified</pose><truncated>0</truncated><difficult>0</difficult><bndbox><xmin>149.4737</xmin><ymin>429.1948</ymin><xmax>248.42105</xmax><ymax>536.4935</ymax></bndbox></object><object><name>coconut</name><pose>Unspecified</pose><truncated>0</truncated><difficult>0</difficult><bndbox><xmin>65.26315</xmin><ymin>427.0909</ymin><xmax>143.1579</xmax><ymax>519.66235</ymax></bndbox></object><object><name>coconut</name><pose>Unspecified</pose><truncated>0</truncated><difficult>0</difficult><bndbox><xmin>65.26315</xmin><ymin>363.97403</ymin><xmax>183.1579</xmax><ymax>450.23376</ymax></bndbox></object><object><name>coconut</name><pose>Unspecified</pose><truncated>0</truncated><difficult>0</difficult><bndbox><xmin>58.94737</xmin><ymin>519.66235</ymin><xmax>155.78947</xmax><ymax>622.75323</ymax></bndbox></object><object><name>coconut</name><pose>Unspecified</pose><truncated>0</truncated><difficult>0</difficult><bndbox><xmin>477.8947</xmin><ymin>269.2987</ymin><xmax>595.7895</xmax><ymax>363.97403</ymax></bndbox></object><object><name>coconut</name><pose>Unspecified</pose><truncated>0</truncated><difficult>0</difficult><bndbox><xmin>368.42105</xmin><ymin>271.4026</ymin><xmax>480.0</xmax><ymax>370.28574</ymax></bndbox></object><object><name>coconut</name><pose>Unspecified</pose><truncated>0</truncated><difficult>0</difficult><bndbox><xmin>258.94736</xmin><ymin>262.987</ymin><xmax>374.73685</xmax><ymax>355.55844</ymax></bndbox></object><object><name>coconut</name><pose>Unspecified</pose><truncated>0</truncated><difficult>0</difficult><bndbox><xmin>172.63159</xmin><ymin>258.7792</ymin><xmax>263.1579</xmax><ymax>351.35065</ymax></bndbox></object><object><name>coconut</name><pose>Unspecified</pose><truncated>0</truncated><difficult>0</difficult><bndbox><xmin>75.789474</xmin><ymin>256.67532</ymin><xmax>183.1579</xmax><ymax>359.76624</ymax></bndbox></object><object><name>coconut</name><pose>Unspecified</pose><truncated>0</truncated><difficult>0</difficult><bndbox><xmin>477.8947</xmin><ymin>349.24677</ymin><xmax>602.1053</xmax><ymax>462.85715</ymax></bndbox></object><object><name>coconut</name><pose>Unspecified</pose><truncated>0</truncated><difficult>0</difficult><bndbox><xmin>589.4737</xmin><ymin>338.72726</ymin><xmax>698.9473</xmax><ymax>433.4026</ymax></bndbox></object><object><name>coconut</name><pose>Unspecified</pose><truncated>0</truncated><difficult>0</difficult><bndbox><xmin>713.6842</xmin><ymin>302.96103</ymin><xmax>823.15796</xmax><ymax>424.987</ymax></bndbox></object><object><name>coconut</name><pose>Unspecified</pose><truncated>0</truncated><difficult>0</difficult><bndbox><xmin>258.94736</xmin><ymin>525.974</ymin><xmax>357.89474</xmax><ymax>618.5455</ymax></bndbox></object><object><name>coconut</name><pose>Unspecified</pose><truncated>0</truncated><difficult>0</difficult><bndbox><xmin>178.94737</xmin><ymin>340.83118</ymin><xmax>252.63158</xmax><ymax>416.5714</ymax></bndbox></object><object><name>coconut</name><pose>Unspecified</pose><truncated>0</truncated><difficult>0</difficult><bndbox><xmin>658.9474</xmin><ymin>414.46756</ymin><xmax>749.4737</xmax><ymax>504.93506</ymax></bndbox></object><object><name>coconut</name><pose>Unspecified</pose><truncated>0</truncated><difficult>0</difficult><bndbox><xmin>0.0</xmin><ymin>441.81818</ymin><xmax>56.842106</xmax><ymax>517.5584</ymax></bndbox></object><object><name>coconut</name><pose>Unspecified</pose><truncated>0</truncated><difficult>0</difficult><bndbox><xmin>0.0</xmin><ymin>519.66235</ymin><xmax>58.94737</xmax><ymax>610.1299</ymax></bndbox></object><object><name>coconut</name><pose>Unspecified</pose><truncated>0</truncated><difficult>0</difficult><bndbox><xmin>151.57895</xmin><ymin>515.4545</ymin><xmax>244.21051</xmax><ymax>616.4416</ymax></bndbox></object></annotation>