<annotation><folder>test_xmls1</folder><filename>341.jpg</filename><path>./images341.jpg</path><source><database>Unknown</database></source><size><width>1200</width><height>706</height><depth>3</depth></size><segmented>0</segmented><object><name>coconut</name><pose>Unspecified</pose><truncated>0</truncated><difficult>0</difficult><bndbox><xmin>316.37717</xmin><ymin>328.42404</ymin><xmax>409.42926</xmax><ymax>438.64346</ymax></bndbox></object><object><name>coconut</name><pose>Unspecified</pose><truncated>0</truncated><difficult>0</difficult><bndbox><xmin>420.59555</xmin><ymin>321.72153</ymin><xmax>535.98016</xmax><ymax>466.94302</ymax></bndbox></object><object><name>coconut</name><pose>Unspecified</pose><truncated>0</truncated><difficult>0</difficult><bndbox><xmin>585.8561</xmin><ymin>332.14767</ymin><xmax>688.58563</xmax><ymax>446.09073</ymax></bndbox></object><object><name>coconut</name><pose>Unspecified</pose><truncated>0</truncated><difficult>0</difficult><bndbox><xmin>835.2357</xmin><ymin>398.42828</ymin><xmax>956.5757</xmax><ymax>522.7975</ymax></bndbox></object><object><name>coconut</name><pose>Unspecified</pose><truncated>0</truncated><difficult>0</difficult><bndbox><xmin>1083.1266</xmin><ymin>239.80168</ymin><xmax>1177.6675</xmax><ymax>344.0633</ymax></bndbox></object><object><name>coconut</name><pose>Unspecified</pose><truncated>0</truncated><difficult>0</difficult><bndbox><xmin>967.74194</xmin><ymin>370.1287</ymin><xmax>1096.526</xmax><ymax>507.1582</ymax></bndbox></object><object><name>coconut</name><pose>Unspecified</pose><truncated>0</truncated><difficult>0</difficult><bndbox><xmin>942.43176</xmin><ymin>132.56117</ymin><xmax>1056.3275</xmax><ymax>256.9304</ymax></bndbox></object><object><name>coconut</name><pose>Unspecified</pose><truncated>0</truncated><difficult>0</difficult><bndbox><xmin>312.6551</xmin><ymin>195.11813</ymin><xmax>404.96277</xmax><ymax>315.7637</ymax></bndbox></object><object><name>coconut</name><pose>Unspecified</pose><truncated>0</truncated><difficult>0</difficult><bndbox><xmin>189.8263</xmin><ymin>178.73418</ymin><xmax>292.55585</xmax><ymax>268.84598</ymax></bndbox></object><object><name>coconut</name><pose>Unspecified</pose><truncated>0</truncated><difficult>0</difficult><bndbox><xmin>2.9776676</xmin><ymin>335.8713</ymin><xmax>84.86352</xmax><ymax>452.79324</ymax></bndbox></object><object><name>coconut</name><pose>Unspecified</pose><truncated>0</truncated><difficult>0</difficult><bndbox><xmin>396.7742</xmin><ymin>573.43884</ymin><xmax>503.2258</xmax><ymax>694.08435</ymax></bndbox></object><object><name>coconut</name><pose>Unspecified</pose><truncated>0</truncated><difficult>0</difficult><bndbox><xmin>573.94543</xmin><ymin>225.6519</ymin><xmax>664.01984</xmax><ymax>331.40295</ymax></bndbox></object><object><name>coconut</name><pose>Unspecified</pose><truncated>0</truncated><difficult>0</difficult><bndbox><xmin>1057.0719</xmin><ymin>5.2130804</ymin><xmax>1149.3796</xmax><ymax>105.00633</ymax></bndbox></object><object><name>coconut</name><pose>Unspecified</pose><truncated>0</truncated><difficult>0</difficult><bndbox><xmin>696.7742</xmin><ymin>230.86497</ymin><xmax>792.80396</xmax><ymax>345.55273</ymax></bndbox></object></annotation>