<annotation><folder>test_xmls1</folder><filename>344.jpg</filename><path>./images344.jpg</path><source><database>Unknown</database></source><size><width>1200</width><height>726</height><depth>3</depth></size><segmented>0</segmented><object><name>coconut</name><pose>Unspecified</pose><truncated>0</truncated><difficult>0</difficult><bndbox><xmin>66.976746</xmin><ymin>395.11154</ymin><xmax>168.8372</xmax><ymax>519.3692</ymax></bndbox></object><object><name>coconut</name><pose>Unspecified</pose><truncated>0</truncated><difficult>0</difficult><bndbox><xmin>336.27905</xmin><ymin>276.43845</ymin><xmax>429.76746</xmax><ymax>376.96155</ymax></bndbox></object><object><name>coconut</name><pose>Unspecified</pose><truncated>0</truncated><difficult>0</difficult><bndbox><xmin>618.1395</xmin><ymin>371.37692</ymin><xmax>707.44183</xmax><ymax>480.27695</ymax></bndbox></object><object><name>coconut</name><pose>Unspecified</pose><truncated>0</truncated><difficult>0</difficult><bndbox><xmin>639.06976</xmin><ymin>60.03462</ymin><xmax>740.9302</xmax><ymax>166.1423</ymax></bndbox></object><object><name>coconut</name><pose>Unspecified</pose><truncated>0</truncated><difficult>0</difficult><bndbox><xmin>315.34885</xmin><ymin>122.86154</ymin><xmax>404.65118</xmax><ymax>228.96924</ymax></bndbox></object><object><name>coconut</name><pose>Unspecified</pose><truncated>0</truncated><difficult>0</difficult><bndbox><xmin>707.44183</xmin><ymin>177.31154</ymin><xmax>803.72095</xmax><ymax>284.8154</ymax></bndbox></object></annotation>