<annotation><folder>test_xmls</folder><filename>39.jpg</filename><path>./images39.jpg</path><source><database>Unknown</database></source><size><width>1200</width><height>869</height><depth>3</depth></size><segmented>0</segmented><object><name>coconut</name><pose>Unspecified</pose><truncated>0</truncated><difficult>0</difficult><bndbox><xmin>473.8574</xmin><ymin>579.3334</ymin><xmax>563.80255</xmax><ymax>689.05554</ymax></bndbox></object><object><name>coconut</name><pose>Unspecified</pose><truncated>0</truncated><difficult>0</difficult><bndbox><xmin>537.4771</xmin><ymin>522.2778</ymin><xmax>634.00366</xmax><ymax>599.0833</ymax></bndbox></object><object><name>coconut</name><pose>Unspecified</pose><truncated>0</truncated><difficult>0</difficult><bndbox><xmin>616.45337</xmin><ymin>465.22223</ymin><xmax>704.2048</xmax><ymax>557.3889</ymax></bndbox></object><object><name>coconut</name><pose>Unspecified</pose><truncated>0</truncated><difficult>0</difficult><bndbox><xmin>704.2048</xmin><ymin>384.02777</ymin><xmax>809.5064</xmax><ymax>491.55554</ymax></bndbox></object><object><name>coconut</name><pose>Unspecified</pose><truncated>0</truncated><difficult>0</difficult><bndbox><xmin>774.4059</xmin><ymin>326.97223</ymin><xmax>866.5448</xmax><ymax>419.1389</ymax></bndbox></object><object><name>coconut</name><pose>Unspecified</pose><truncated>0</truncated><difficult>0</difficult><bndbox><xmin>833.638</xmin><ymin>258.94446</ymin><xmax>932.35834</xmax><ymax>359.8889</ymax></bndbox></object><object><name>coconut</name><pose>Unspecified</pose><truncated>0</truncated><difficult>0</difficult><bndbox><xmin>925.777</xmin><ymin>201.88889</ymin><xmax>1033.2723</xmax><ymax>296.25</ymax></bndbox></object><object><name>coconut</name><pose>Unspecified</pose><truncated>0</truncated><difficult>0</difficult><bndbox><xmin>1015.72217</xmin><ymin>140.44444</ymin><xmax>1114.4424</xmax><ymax>239.19444</ymax></bndbox></object><object><name>coconut</name><pose>Unspecified</pose><truncated>0</truncated><difficult>0</difficult><bndbox><xmin>1085.9232</xmin><ymin>223.83333</ymin><xmax>1153.9305</xmax><ymax>291.8611</ymax></bndbox></object><object><name>coconut</name><pose>Unspecified</pose><truncated>0</truncated><difficult>0</difficult><bndbox><xmin>1105.6672</xmin><ymin>50.47222</ymin><xmax>1193.4187</xmax><ymax>144.83334</ymax></bndbox></object><object><name>coconut</name><pose>Unspecified</pose><truncated>0</truncated><difficult>0</difficult><bndbox><xmin>469.46985</xmin><ymin>735.1389</ymin><xmax>552.8336</xmax><ymax>818.5278</ymax></bndbox></object><object><name>coconut</name><pose>Unspecified</pose><truncated>0</truncated><difficult>0</difficult><bndbox><xmin>541.86475</xmin><ymin>678.0833</ymin><xmax>627.42236</xmax><ymax>752.69446</ymax></bndbox></object><object><name>coconut</name><pose>Unspecified</pose><truncated>0</truncated><difficult>0</difficult><bndbox><xmin>370.74954</xmin><ymin>642.9722</ymin><xmax>500.1828</xmax><ymax>748.30554</ymax></bndbox></object><object><name>coconut</name><pose>Unspecified</pose><truncated>0</truncated><difficult>0</difficult><bndbox><xmin>324.68008</xmin><ymin>752.69446</ymin><xmax>401.46252</xmax><ymax>827.3056</ymax></bndbox></object><object><name>coconut</name><pose>Unspecified</pose><truncated>0</truncated><difficult>0</difficult><bndbox><xmin>620.841</xmin><ymin>625.4167</ymin><xmax>684.4607</xmax><ymax>680.2778</ymax></bndbox></object><object><name>coconut</name><pose>Unspecified</pose><truncated>0</truncated><difficult>0</difficult><bndbox><xmin>684.4607</xmin><ymin>539.8333</ymin><xmax>761.24316</xmax><ymax>618.8333</ymax></bndbox></object><object><name>coconut</name><pose>Unspecified</pose><truncated>0</truncated><difficult>0</difficult><bndbox><xmin>754.6618</xmin><ymin>493.75</ymin><xmax>857.76965</xmax><ymax>583.7222</ymax></bndbox></object><object><name>coconut</name><pose>Unspecified</pose><truncated>0</truncated><difficult>0</difficult><bndbox><xmin>19.744059</xmin><ymin>166.77777</ymin><xmax>72.39488</xmax><ymax>250.16666</ymax></bndbox></object><object><name>coconut</name><pose>Unspecified</pose><truncated>0</truncated><difficult>0</difficult><bndbox><xmin>98.72029</xmin><ymin>256.75</ymin><xmax>190.85924</xmax><ymax>346.7222</ymax></bndbox></object><object><name>coconut</name><pose>Unspecified</pose><truncated>0</truncated><difficult>0</difficult><bndbox><xmin>96.526505</xmin><ymin>164.58333</ymin><xmax>177.69653</xmax><ymax>239.19444</ymax></bndbox></object><object><name>coconut</name><pose>Unspecified</pose><truncated>0</truncated><difficult>0</difficult><bndbox><xmin>344.42413</xmin><ymin>87.77778</ymin><xmax>427.78793</xmax><ymax>171.16667</ymax></bndbox></object></annotation>